llm_mapreduce/__init__.py
llm_mapreduce/confidence_calibration.py
llm_mapreduce/mapreduce.py
llm_mapreduce/structured_info_protocol.py
llm_mapreduce/utils.py
tests/__init__.py
tests/test_confidence_calibration.py
tests/test_mapreduce.py
tests/test_structured_info_protocol.py
llm_mapreduce-0.1.0.dist-info/LICENSE
llm_mapreduce-0.1.0.dist-info/METADATA
llm_mapreduce-0.1.0.dist-info/WHEEL
llm_mapreduce-0.1.0.dist-info/top_level.txt
llm_mapreduce-0.1.0.dist-info/RECORD
