Metadata-Version: 2.1
Name: llm_mapreduce
Version: 0.1.0
Summary: MapReduce-inspired framework for extending context windows in large language models
Home-page: https://github.com/Godskid89/LLM_MapReduce
Author: Joseph Oladokun
Author-email: oladokunjoseph2@example.com
Classifier: Programming Language :: Python :: 3
Classifier: License :: OSI Approved :: MIT License
Classifier: Operating System :: OS Independent
Requires-Python: >=3.7
License-File: LICENSE
Requires-Dist: tqdm>=4.62.0
Requires-Dist: pytest>=7.0.0
Provides-Extra: huggingface
Requires-Dist: transformers>=4.0.0; extra == "huggingface"
Provides-Extra: openai
Requires-Dist: openai>=0.27.0; extra == "openai"
